pycountries/__init__.py
pycountries/_base.py
pycountries/countries.py
pycountries/currencies.py
pycountries/languages.py
pycountries/macro_languages.py
pycountries/phones.py
pycountries-1.2.1.dist-info/LICENSE.md
pycountries-1.2.1.dist-info/METADATA
pycountries-1.2.1.dist-info/WHEEL
pycountries-1.2.1.dist-info/top_level.txt
pycountries-1.2.1.dist-info/RECORD
