Metadata-Version: 2.1
Name: pycountries
Version: 1.2.1
Summary: List of existing countries and currencies
Home-page: https://github.com/koldakov/pycountries
Author: Ivan Koldakov
Author-email: Ivan Koldakov <ivan@koldakov.com>
License: MIT License
Project-URL: Homepage, https://github.com/koldakov/pycountries
Project-URL: Issues, https://github.com/koldakov/pycountries/issues
Keywords: pydantic,fastapi,countries,currencies
Classifier: Programming Language :: Python :: 3
Classifier: License :: OSI Approved :: MIT License
Classifier: Operating System :: OS Independent
Requires-Python: >=3.8
License-File: LICENSE.md
Requires-Dist: pydantic >=1.5
